_pyngraph.cp37-win_amd64.pyd
ngraph/__init__.py
ngraph/exceptions.py
ngraph/helpers.py
ngraph/opset_utils.py
ngraph/impl/__init__.py
ngraph/impl/op/__init__.py
ngraph/impl/op/util/__init__.py
ngraph/impl/passes/__init__.py
ngraph/opset1/__init__.py
ngraph/opset1/ops.py
ngraph/opset2/__init__.py
ngraph/opset2/ops.py
ngraph/opset3/__init__.py
ngraph/opset3/ops.py
ngraph/opset4/__init__.py
ngraph/opset4/ops.py
ngraph/utils/__init__.py
ngraph/utils/broadcasting.py
ngraph/utils/decorators.py
ngraph/utils/input_validation.py
ngraph/utils/node_factory.py
ngraph/utils/reduction.py
ngraph/utils/tensor_iterator_types.py
ngraph/utils/types.py
openvino/__init__.py
openvino/inference_engine/__init__.py
openvino/inference_engine/constants.cp37-win_amd64.pyd
openvino/inference_engine/ie_api.cp37-win_amd64.pyd
openvino_python-2021.1-110.3.data/data/Library/bin/HeteroPlugin.dll
openvino_python-2021.1-110.3.data/data/Library/bin/MKLDNNPlugin.dll
openvino_python-2021.1-110.3.data/data/Library/bin/MultiDevicePlugin.dll
openvino_python-2021.1-110.3.data/data/Library/bin/cache.json
openvino_python-2021.1-110.3.data/data/Library/bin/clDNNPlugin.dll
openvino_python-2021.1-110.3.data/data/Library/bin/inference_engine.dll
openvino_python-2021.1-110.3.data/data/Library/bin/inference_engine_c_api.dll
openvino_python-2021.1-110.3.data/data/Library/bin/inference_engine_ir_reader.dll
openvino_python-2021.1-110.3.data/data/Library/bin/inference_engine_legacy.dll
openvino_python-2021.1-110.3.data/data/Library/bin/inference_engine_lp_transformations.dll
openvino_python-2021.1-110.3.data/data/Library/bin/inference_engine_onnx_reader.dll
openvino_python-2021.1-110.3.data/data/Library/bin/inference_engine_preproc.dll
openvino_python-2021.1-110.3.data/data/Library/bin/inference_engine_transformations.dll
openvino_python-2021.1-110.3.data/data/Library/bin/myriadPlugin.dll
openvino_python-2021.1-110.3.data/data/Library/bin/myriad_compile.exe
openvino_python-2021.1.dist-info/METADATA
openvino_python-2021.1.dist-info/WHEEL
openvino_python-2021.1.dist-info/top_level.txt
openvino_python-2021.1.dist-info/RECORD
