Metadata-Version: 2.1
Name: openvino-python
Version: 2021.1
Summary: Inference Engine Python* API
Home-page: UNKNOWN
Author: Intel Corporation
Author-email: openvino_pushbot@intel.com
License: Proprietary - Intel
Platform: UNKNOWN
Requires-Dist: numpy (==1.16.3)
